defang_api/__init__.py
defang_api/servelocal.py
defang_api/helpers/__init__.py
defang_api/helpers/helpers.py
defang_api/helpers/parsers.py
defang_api-0.0.1.dist-info/METADATA
defang_api-0.0.1.dist-info/WHEEL
defang_api-0.0.1.dist-info/entry_points.txt
defang_api-0.0.1.dist-info/top_level.txt
defang_api-0.0.1.dist-info/RECORD
