Metadata-Version: 2.1
Name: defang-api
Version: 0.0.1
Summary: Example defang API Server
Home-page: https://github.com/zpriddy/defang_api
Author: Zachary Priddy
Author-email: py@zpriddy.com
License: BSD-derived (http://www.repoze.org/LICENSE.txt)
Project-URL: Bug Tracker, https://github.com/zpriddy/defang_api/issues
Project-URL: Blog, https:/zpriddy.com
Project-URL: Source Code, https://github.com/zpriddy/defang_api/
Keywords: defang
Platform: UNKNOWN
Classifier: Development Status :: 3 - Alpha
Classifier: Intended Audience :: Developers
Classifier: Topic :: Software Development :: Build Tools
Classifier: License :: OSI Approved :: Apache Software License
Classifier: Programming Language :: Python :: 3
Classifier: Programming Language :: Python :: 3.5
Classifier: Programming Language :: Python :: 3.6
Classifier: Programming Language :: Python :: 3.7
Classifier: Programming Language :: Python :: 3.8
Requires-Python: >=3.7
Requires-Dist: Flask
Requires-Dist: flask-restx
Provides-Extra: testing
Requires-Dist: pytest ; extra == 'testing'
Requires-Dist: pytest-cov ; extra == 'testing'
Requires-Dist: coverage ; extra == 'testing'
